defender/__init__.py
defender/admin.py
defender/apps.py
defender/ci_settings.py
defender/config.py
defender/connection.py
defender/data.py
defender/decorators.py
defender/middleware.py
defender/models.py
defender/signals.py
defender/tasks.py
defender/test.py
defender/test_settings.py
defender/test_urls.py
defender/tests.py
defender/urls.py
defender/utils.py
defender/views.py
defender/management/__init__.py
defender/management/commands/__init__.py
defender/management/commands/cleanup_django_defender.py
defender/migrations/0001_initial.py
defender/migrations/__init__.py
defender/templates/admin/defender/app_index.html
defender/templates/defender/lockout.html
defender/templates/defender/admin/blocks.html
exampleapp/__init__.py
exampleapp/defender.sb
exampleapp/readme.md
exampleapp/settings.py
exampleapp/urls.py
exampleapp/utils.py
django_defender-0.9.7.dist-info/LICENSE
django_defender-0.9.7.dist-info/METADATA
django_defender-0.9.7.dist-info/WHEEL
django_defender-0.9.7.dist-info/top_level.txt
django_defender-0.9.7.dist-info/RECORD
